[
    {
        "projectTitle": "CLIENT CONNECT",
        "collaborators": "Solo Project",
        "sourceCode": "https://github.com/beejay321/ClientConnect",
        "live": "https://clientconnect-fawn.vercel.app/",
        "description": "A marketplace website to connect freelancers to clients with freelance job. Freelancers have the ability to bid for projects they believe they are qualified for and the clients will choose which freelancers they feel suits best.",
        "skills": [
            "HTML5",
            "CSS",
            "JavaScript",
            "React",
            "Redux",
            "Bootstrap",
            "Node.js",
            "MongoDB",
            "OAuth",
            "GIT"
        ],
        "images": [
            "https://res.cloudinary.com/dvyids286/image/upload/v1647438177/portfolio/cd4vyhogj01rxdkrskxe.png",
            "https://res.cloudinary.com/dvyids286/image/upload/v1647437986/portfolio/cbx0qjk6f4qcyqod1bxg.png",
            "https://res.cloudinary.com/dvyids286/image/upload/v1647437879/portfolio/qikfx7jc0wx9pmh5zowp.png",
            "https://res.cloudinary.com/dvyids286/image/upload/v1647437932/portfolio/cexupoloxeaxvqga6uos.png"
        ]
    },
    {
        "projectTitle": "WEATHERSAYS",
        "collaborators": "Solo Project",
        "sourceCode": "https://github.com/beejay321/MyWeather_App",
        "live": "https://weather-says.vercel.app/",
        "description": "A website that basically tells the weather conditions for different locations if searched for.",
        "skills": [
            "HTML5",
            "CSS",
            "TypeScript",
            "React",
            "Bootstrap",
            "GIT"
        ],
        "images": [
            "https://res.cloudinary.com/dvyids286/image/upload/v1647619558/portfolio/ox46wprmo4x1qq9qumnw.png"
        ]
    },
    {
        "projectTitle": "TRAVELGO",
        "collaborators": "Solo Project",
        "sourceCode": "https://github.com/beejay321/Travel_go",
        "live": "",
        "description": "A travel log website for travellers get relevant information about prosective vacation destinations and also share experiences and information on previous vacation destinations.",
        "skills": [
            "HTML5",
            "CSS",
            "JavaScript",
            "React",
            "Bootstrap",
            "Node.js",
            "MongoDB",
            "GIT"
        ],
        "images": [
            "https://via.placeholder.com/600x350"
        ]
    }
    
]